{
    "name": "Funcionario",
    "fields": [
        {
            "fieldName": "nome",
            "fieldType": "String"
        },
        {
            "fieldName": "endereco",
            "fieldType": "String"
        },
        {
            "fieldName": "telefone",
            "fieldType": "String"
        },
        {
            "fieldName": "numVeiculoAbordado",
            "fieldType": "Integer"
        },
        {
            "fieldName": "numDocApreendido",
            "fieldType": "Integer"
        }
    ],
    "relationships": [
        {
            "relationshipType": "many-to-one",
            "relationshipName": "supervisor",
            "otherEntityName": "funcionario",
            "otherEntityField": "id"
        },
        {
            "relationshipType": "many-to-one",
            "relationshipName": "chefe",
            "otherEntityName": "funcionario",
            "otherEntityField": "id"
        },
        {
            "relationshipType": "many-to-one",
            "relationshipName": "gerente",
            "otherEntityName": "funcionario",
            "otherEntityField": "id"
        },
        {
            "relationshipType": "many-to-one",
            "relationshipName": "departamento",
            "otherEntityName": "departamento",
            "otherEntityField": "id"
        },
        {
            "relationshipType": "many-to-one",
            "relationshipName": "cargo",
            "otherEntityName": "cargo",
            "otherEntityField": "id"
        }
    ],
    "changelogDate": "20181022233201",
    "entityTableName": "funcionario",
    "dto": "no",
    "pagination": "no",
    "service": "no",
    "jpaMetamodelFiltering": false,
    "fluentMethods": true,
    "clientRootFolder": "",
    "applications": "*"
}